README
setup.py
Klarna_API.egg-info/PKG-INFO
Klarna_API.egg-info/SOURCES.txt
Klarna_API.egg-info/dependency_links.txt
Klarna_API.egg-info/top_level.txt
klarna/__init__.py
klarna/addr.py
klarna/calc.py
klarna/candice.py
klarna/config.py
klarna/const.py
klarna/digest.py
klarna/error.py
klarna/ilt.py
klarna/klarna.py
klarna/pclass.py
klarna/util.py
klarna/checkout/ThreatMetrix.py
klarna/checkout/__init__.py
klarna/checkout/checkouthtml.py
klarna/kex/__init__.py
klarna/pclasses/__init__.py
klarna/pclasses/jsonstorage.py
klarna/pclasses/storage.py