Metadata-Version: 1.1
Name: Klarna-API
Version: 3.0.1
Summary: The Klarna API used to communicate with Klarna Online
Home-page: https://developers.klarna.com
Author: Merchant Integration
Author-email: support@klarna.com
License: BSD
Keywords: klarna xmlrpc payment
Platform: UNKNOWN
Classifier: Development Status :: 5 - Production/Stable
Classifier: Intended Audience :: Developers
Classifier: License :: OSI Approved :: BSD License
Classifier: Natural Language :: English
Classifier: Operating System :: OS Independent
Classifier: Programming Language :: Python
Classifier: Programming Language :: Python :: 2
Classifier: Programming Language :: Python :: 3
Classifier: Topic :: Software Development :: Libraries :: Python Modules
